db_help/__init__.py
db_help/mysql.py
db_help/qdrant.py
db_help-0.2.2.dist-info/METADATA
db_help-0.2.2.dist-info/WHEEL
db_help-0.2.2.dist-info/top_level.txt
db_help-0.2.2.dist-info/RECORD
