Metadata-Version: 2.4
Name: db-help
Version: 0.2.2
Summary: Add your description here
Requires-Python: >=3.12
Requires-Dist: anyio>=4.10.0
Requires-Dist: dotenv>=0.9.9
Requires-Dist: fastapi>=0.116.2
Requires-Dist: mysql-connector-python>=9.4.0
Requires-Dist: pymysql>=1.1.2
Requires-Dist: pytest>=8.4.2
Requires-Dist: pytest-asyncio>=1.2.0
Requires-Dist: pytest-tornasync>=0.6.0.post2
Requires-Dist: qdrant-client>=1.15.1
Requires-Dist: requests>=2.32.5
Requires-Dist: sqlalchemy>=2.0.43
Requires-Dist: toml>=0.10.2
Requires-Dist: uvicorn>=0.35.0
Requires-Dist: volcengine-python-sdk==4.0.6
